iupdatable/__init__.py
iupdatable/__version__.py
iupdatable/file.py
iupdatable-0.0.1.dist-info/LICENSE
iupdatable-0.0.1.dist-info/METADATA
iupdatable-0.0.1.dist-info/WHEEL
iupdatable-0.0.1.dist-info/top_level.txt
iupdatable-0.0.1.dist-info/RECORD
