Metadata-Version: 2.1
Name: iupdatable
Version: 0.0.1
Summary: 常用函数封装
Home-page: https://www.cnblogs.com/IUpdatable/
Author: IUpdatable
Author-email: IUpdatable@163.com
License: MIT
Platform: UNKNOWN
Classifier: License :: OSI Approved :: MIT License
Classifier: Programming Language :: Python
Classifier: Programming Language :: Python :: 3
Classifier: Programming Language :: Python :: 3.6
Classifier: Programming Language :: Python :: Implementation :: CPython
Classifier: Programming Language :: Python :: Implementation :: PyPy
Requires-Python: >=3.6.0
